setup.py
baby/__init__.py
baby.egg-info/PKG-INFO
baby.egg-info/SOURCES.txt
baby.egg-info/dependency_links.txt
baby.egg-info/not-zip-safe
baby.egg-info/pbr.json
baby.egg-info/top_level.txt