Metadata-Version: 1.1
Name: baby
Version: 0.0.1
Summary: Baby Announcement
Home-page: https://www.github.com/swampdragons/baby
Author: Megan Marsh
Author-email: megan.n.marsh@gmail.com
License: UNKNOWN
Platform: UNKNOWN
Classifier: Development Status :: 3 - Alpha
Classifier: Intended Audience :: Developers
Classifier: Operating System :: OS Independent
Classifier: Programming Language :: Python :: 2.7
